timecalculator/__init__.py
timecalculator-1.2.1.dist-info/LICENCE.txt
timecalculator-1.2.1.dist-info/METADATA
timecalculator-1.2.1.dist-info/WHEEL
timecalculator-1.2.1.dist-info/top_level.txt
timecalculator-1.2.1.dist-info/RECORD
