Metadata-Version: 2.1
Name: timecalculator
Version: 1.2.1
Summary: A Python package for converting time units to seconds
Home-page: https://github.com/Xyndra/Timecalculator
Author: Xyndra
Author-email: sammy@deutschergamingserver.de
License: MIT
Keywords: time,calculator
Classifier: Development Status :: 5 - Production/Stable
Classifier: Programming Language :: Python :: 3
Classifier: Operating System :: Microsoft :: Windows :: Windows 10
License-File: LICENCE.txt
